<?xml version="1.0" encoding="utf-8"?>
<LanguageData>
  <!--[Core] <ElectricStove.label>電子料理台</ElectricStove.label>-->
  <!--[Core] <ElectricStove.description>用來烹飪食物的工作台。</ElectricStove.description>-->
  <!--[Core] <ElectricStove_Blueprint.label>electric stove (blueprint)</ElectricStove_Blueprint.label>-->
  <!--[Core] <ElectricStove_Blueprint_Install.label>electric stove (blueprint)</ElectricStove_Blueprint_Install.label>-->
  <!--[Core] <ElectricStove_Frame.label>electric stove (building)</ElectricStove_Frame.label>-->
  <!--[Core] <ElectricStove_Frame.description>An electrically-powered stove with an attached countertop for preparing meals.</ElectricStove_Frame.description>-->
  <!--[Core] <FueledStove.label>爐灶</FueledStove.label>-->
  <!--[Core] <FueledStove.description>燃燒木材烹調食物的工作台。</FueledStove.description>-->
  <!--[Core] <FueledStove_Blueprint.label>fueled stove (blueprint)</FueledStove_Blueprint.label>-->
  <!--[Core] <FueledStove_Blueprint_Install.label>fueled stove (blueprint)</FueledStove_Blueprint_Install.label>-->
  <!--[Core] <FueledStove_Frame.label>fueled stove (building)</FueledStove_Frame.label>-->
  <!--[Core] <FueledStove_Frame.description>A wood-fueled stove with an attached countertop for preparing meals.</FueledStove_Frame.description>-->
</LanguageData>